__init__.py
request_builder/__init__.py
request_builder/abstract_request_builder.py
request_builder/json_request_builder.py
request_builder/raw_request_builder.py
request_builder/xml_request_builder.py
requests_builder-1.0.0.dist-info/LICENSE
requests_builder-1.0.0.dist-info/METADATA
requests_builder-1.0.0.dist-info/WHEEL
requests_builder-1.0.0.dist-info/top_level.txt
requests_builder-1.0.0.dist-info/RECORD
