Metadata-Version: 2.1
Name: requests-builder
Version: 1.0.0
Summary: A helper package for building HTTP requests with the requests package
Author-email: Dor Genosar <dor.genosar@outlook.com>
Project-URL: Homepage, https://github.com/labrador-team/request-builder
Project-URL: Issues, https://github.com/labrador-team/request-builder/issues
Keywords: Requests,HTTP
Classifier: Programming Language :: Python :: 3
Classifier: Development Status :: 4 - Beta
Classifier: License :: OSI Approved :: Apache Software License
Classifier: Operating System :: OS Independent
Classifier: Topic :: Internet :: WWW/HTTP
Requires-Python: >=3.8
License-File: LICENSE
Requires-Dist: requests ~=2.31
Requires-Dist: typing-extensions ~=4.11.0
